{"data":[{"medium":"041 \u2013 Das Kulturmagazin","ressort":"","jahr":"2018","lohn":"500","sozialleistungen":"AHV","spesen":"nein","abrechnung":"pauschal","zeichen":"10000 Zeichen","auftrag":"eigene Geschichte","infos":"","logo":"041"},{"medium":"20 Minuten","ressort":"Region Bern","jahr":"2018","lohn":"300","sozialleistungen":"","spesen":"nein","abrechnung":"Tagesansatz","zeichen":"","auftrag":"","infos":"","logo":"20min"},{"medium":"Aargauer Zeitung","ressort":"Ausland","jahr":"2018","lohn":"300","sozialleistungen":"AHV und PK","spesen":"nein","abrechnung":"pro Zeile","zeichen":"4000 Zeichen","auftrag":"eigene Geschichte","infos":"","logo":"az"},{"medium":"Aargauer Zeitung","ressort":"","jahr":"2017","lohn":"100","sozialleistungen":"AHV und ALV","spesen":"","abrechnung":"pauschal","zeichen":"3500 Zeichen","auftrag":"","infos":"Zweitpublikation","logo":"az"},{"medium":"Aargauer Zeitung","ressort":"","jahr":"2013","lohn":"500","sozialleistungen":"","spesen":"","abrechnung":"pauschal","zeichen":"6600 Zeichen","auftrag":"","infos":"","logo":"az"},{"medium":"Anzeiger aus dem Bezirk Affoltern","ressort":"","jahr":"2018","lohn":"","sozialleistungen":"","spesen":"","abrechnung":"","zeichen":"pro Zeile 1 Franken, pro Bild 50 Franken","auftrag":"","infos":"","logo":"anzeigeraffoltern"},{"medium":"B\u00e4rner B\u00e4r","ressort":"Portr\u00e4t","jahr":"2018","lohn":"300","sozialleistungen":"","spesen":"Keine","abrechnung":"pauschal","zeichen":"3500-4500 Zeichen inkl. Leerschl\u00e4ge","auftrag":"Auftragsarbeit","infos":"Aufwand vor Ort im Schnitt eine Stunde","logo":"baernerbaer"},{"medium":"Basler Zeitung","ressort":"Region","jahr":"2018","lohn":"250","sozialleistungen":"AHV, ALV und PK","spesen":"ja","abrechnung":"pauschal","zeichen":"3500 Zeichen","auftrag":"Auftragsarbeit","infos":"","logo":"baz"},{"medium":"Basler Zeitung","ressort":"Region","jahr":"2018","lohn":"200","sozialleistungen":"AHV, ALV und PK","spesen":"ja","abrechnung":"pauschal","zeichen":"3000 Zeichen","auftrag":"Auftragsarbeit","infos":"","logo":"baz"},{"medium":"Beobachter","ressort":"","jahr":"2016","lohn":"2500","sozialleistungen":"AHV, ALV und PK","spesen":"nein","abrechnung":"pauschal","zeichen":"","auftrag":"eigene Geschichte","infos":"Reportage, aufw\u00e4ndige Recherche","logo":"beobachter"},{"medium":"Beobachter","ressort":"","jahr":"2018","lohn":"3000","sozialleistungen":"AHV und PK","spesen":"Zug, 40 Franken Infrastrukturentsch\u00e4digung","abrechnung":"Tagesansatz","zeichen":"11000 Zeichen","auftrag":"Auftragsarbeit","infos":"","logo":"beobachter"},{"medium":"Beobachter","ressort":"","jahr":"2018","lohn":"3000","sozialleistungen":"AHV und PK","spesen":"Zug","abrechnung":"Tagesansatz","zeichen":"11000 Zeichen","auftrag":"Auftragsarbeit","infos":"","logo":"beobachter"},{"medium":"Beobachter","ressort":"Nachlese","jahr":"2017","lohn":"540","sozialleistungen":"AHV und ALV","spesen":"","abrechnung":"pauschal","zeichen":"2500 Zeichen","auftrag":"eigene Geschichte","infos":"Der Beobachter hat grunds\u00e4tzlich Tageshonorare von um die 500 Franken.\u00a0","logo":"beobachter"},{"medium":"Beobachter","ressort":"Gesellschaft","jahr":"2015","lohn":"3780","sozialleistungen":"keine","spesen":"Infrastrukturpauschale von 40.- pro Tag","abrechnung":"Tagesansatz (500 + 40 Infrastrukturpauschale)","zeichen":"14700 Zeichen","auftrag":"eigene Geschichte","infos":"Aufwand genau erfasst: 125 Stunden (ca. halber Monat)","logo":"beobachter"},{"medium":"Beobachter","ressort":"Gesellschaft","jahr":"2015","lohn":"3240","sozialleistungen":"keine","spesen":"","abrechnung":"Tagesansatz (500 + 40 Infrastrukturpauschale)","zeichen":"12900 Zeichen","auftrag":"eigene Geschichte","infos":"Aufwand 75 Stunden (9 Tage)","logo":"beobachter"},{"medium":"Beobachter","ressort":"Gesellschaft","jahr":"2016","lohn":"4860","sozialleistungen":"keine","spesen":"","abrechnung":"Tagesansatz (500 + 40 Infrastrukturpauschale)","zeichen":"12000 Zeichen","auftrag":"eigene Geschichte","infos":"Mein Rekordhonorar. hat intern f\u00fcr krach gesorgt. Ich weiss, aus erster Hand, dass sie das heute nicht mehr zahlen. 140 Stunden Aufwand. (17 Tage)","logo":"beobachter"},{"medium":"Beobachter","ressort":"Gesellschaft","jahr":"2016","lohn":"540","sozialleistungen":"keine","spesen":"","abrechnung":"Tagesansatz (500 + 40 Infrastrukturpauschale)","zeichen":"eine Seite","auftrag":"eigene Geschichte","infos":"Aufwand 13 Stunden","logo":"beobachter"},{"medium":"Berner Zeitung","ressort":"Stadt Bern","jahr":"2015","lohn":"400","sozialleistungen":"AHV und ALV","spesen":"","abrechnung":"pauschal","zeichen":"","auftrag":"Auftragsarbeit","infos":"Aufwand circa einen Tag","logo":"bernerzeitung"},{"medium":"Berner Zeitung","ressort":"Inland","jahr":"2015","lohn":"370","sozialleistungen":"AHV und ALV","spesen":"Zug","abrechnung":"pauschal","zeichen":"","auftrag":"Auftragsarbeit","infos":"Aufwand circa einen Tag","logo":"bernerzeitung"},{"medium":"Berner Zeitung","ressort":"Schweiz","jahr":"2015","lohn":"400","sozialleistungen":"AHV und ALV","spesen":"Zug","abrechnung":"pauschal","zeichen":"","auftrag":"Auftragsarbeit","infos":"Aufwand circa einen Tag","logo":"bernerzeitung"},{"medium":"Berner Zeitung","ressort":"Ausland","jahr":"2017","lohn":"1100","sozialleistungen":"keine","spesen":"","abrechnung":"Tagesans\u00e4tze + 300 f\u00fcr Publikation in #12-App","zeichen":"8000 Zeichen","auftrag":"eigene Geschichte","infos":"Auslandrecherche","logo":"bernerzeitung"},{"medium":"Berner Zeitung","ressort":"Kultur","jahr":"2017","lohn":"300","sozialleistungen":"keine","spesen":"Zug","abrechnung":"pauschal","zeichen":"4000 Zeichen","auftrag":"Auftragsarbeit","infos":"\u00a0Reportage in anderem Kanton mit Interviews und thematischer Vorrecherche","logo":"bernerzeitung"},{"medium":"Berner Zeitung","ressort":"Kultur","jahr":"2017","lohn":"350","sozialleistungen":"keine","spesen":"nein","abrechnung":"pauschal","zeichen":"4000 Zeichen","auftrag":"Auftragsarbeit","infos":"Investigative Recherche mit mehreren Interviewpartnern, im Laufe einer Woche erarbeitet","logo":"bernerzeitung"},{"medium":"Berner Zeitung","ressort":"Kultur","jahr":"2017","lohn":"250","sozialleistungen":"keine","spesen":"\u00fcbernimmt Spesen wie Zug in der Regel","abrechnung":"pauschal","zeichen":"5000 Zeichen","auftrag":"eigene Geschichte","infos":"aufw\u00e4ndige Recherche und mehrere Interviews","logo":"bernerzeitung"},{"medium":"Berner Zeitung","ressort":"Kultur","jahr":"2017","lohn":"250","sozialleistungen":"keine","spesen":"","abrechnung":"pauschal","zeichen":"3500 Zeichen","auftrag":"Auftragsarbeit","infos":"Buchrezension und Interview mit dem Autor","logo":"bernerzeitung"},{"medium":"Berner Zeitung","ressort":"Sport","jahr":"2018","lohn":"150","sozialleistungen":"AHV und ALV","spesen":"Zug","abrechnung":"pauschal","zeichen":"3000 Zeichen","auftrag":"Auftragsarbeit","infos":"tagesaktueller Bericht","logo":"bernerzeitung"},{"medium":"Berner Zeitung","ressort":"Sport","jahr":"2018","lohn":"150","sozialleistungen":"AHV und ALV","spesen":"Zug","abrechnung":"pauschal","zeichen":"3500 Zeichen","auftrag":"Auftragsarbeit","infos":"tagesaktueller Bericht, wurde ohne zus\u00e4tzliche Entsch\u00e4digung zweitverwertet. Das liegt an der Zusammenf\u00fchrung der Tamedia-Sportredaktionen.","logo":"bernerzeitung"},{"medium":"Bieler Tagblatt","ressort":"Schweiz","jahr":"2017","lohn":"250","sozialleistungen":"keine","spesen":"nein","abrechnung":"1 Franken pro Zeile","zeichen":"120 Zeilen","auftrag":"eigene Geschichte","infos":"","logo":"bielertagblatt"},{"medium":"Bieler Tagblatt","ressort":"Region","jahr":"2018","lohn":"250","sozialleistungen":"AHV und ALV","spesen":"nein","abrechnung":"pauschal","zeichen":"4000 bis 6000 Zeichen","auftrag":"Auftragsarbeit","infos":"tagesaktuell mit Interview","logo":"bielertagblatt"},{"medium":"Binninger Anzeiger","ressort":"Region","jahr":"2018","lohn":"260","sozialleistungen":"keine","spesen":"nein","abrechnung":"pro Stunde","zeichen":"4200 Zeichen","auftrag":"Auftragsarbeit","infos":"","logo":"binningeranzeiger"},{"medium":"bz basel","ressort":"Basel","jahr":"2018","lohn":"180","sozialleistungen":"","spesen":"nein","abrechnung":"pauschal","zeichen":"3500 Zeichen","auftrag":"Auftragsarbeit","infos":"","logo":"bzbasel"},{"medium":"bz basel","ressort":"Kultur","jahr":"2018","lohn":"200","sozialleistungen":"keine","spesen":"","abrechnung":"pauschal","zeichen":"4500 Zeichen","auftrag":"Auftragsarbeit","infos":"","logo":"bzbasel"},{"medium":"Das Magazin","ressort":"","jahr":"2016","lohn":"3000","sozialleistungen":"AHV und ALV","spesen":"Flug und Unterkunft","abrechnung":"pauschal","zeichen":"","auftrag":"eigene Geschichte","infos":"Reportage, hoher Rechercheaufwand","logo":"dasmagazin"},{"medium":"Das Magazin","ressort":"Ein Tag im Leben von","jahr":"2017","lohn":"400","sozialleistungen":"keine","spesen":"nein","abrechnung":"pauschal","zeichen":"6500 Zeichen plus ein Bild","auftrag":"eigene Geschichte","infos":"","logo":"dasmagazin"},{"medium":"Das Magazin","ressort":"Ein Tag im Leben von","jahr":"2017","lohn":"400","sozialleistungen":"AHV, ALV und PK","spesen":"nein","abrechnung":"pauschal","zeichen":"","auftrag":"eigene Geschichte","infos":"Aufwand circa 1,5 Tage","logo":"dasmagazin"},{"medium":"Das Magazin","ressort":"","jahr":"2018","lohn":"400","sozialleistungen":"","spesen":"","abrechnung":"pauschal","zeichen":"4000 Zeichen","auftrag":"Auftragsarbeit","infos":"","logo":"dasmagazin"},{"medium":"Das Magazin","ressort":"Ein Tag im Leben von","jahr":"2018","lohn":"400","sozialleistungen":"AHV","spesen":"","abrechnung":"pauschal","zeichen":"3800 Zeichen","auftrag":"eigene Geschichte","infos":"","logo":"dasmagazin"},{"medium":"Das Magazin","ressort":"Ein Tag im Leben von","jahr":"2018","lohn":"400","sozialleistungen":"AHV und ALV","spesen":"ja, \u00dcbernachtung","abrechnung":"pauschal","zeichen":"3700 Zeichen","auftrag":"eigene Geschichte","infos":"","logo":"dasmagazin"},{"medium":"Das Magazin","ressort":"Ein Tag im Leben von","jahr":"2018","lohn":"400","sozialleistungen":"keine","spesen":"","abrechnung":"pauschal","zeichen":"3800 Zeichen","auftrag":"eigene Geschichte","infos":"","logo":"dasmagazin"},{"medium":"Das Magazin","ressort":"Ein Tag im Leben von","jahr":"2017","lohn":"400","sozialleistungen":"AHV und ALV","spesen":"nein","abrechnung":"pauschal","zeichen":"3800 Zeichen","auftrag":"eigene Geschichte","infos":"","logo":"dasmagazin"},{"medium":"Das Magazin","ressort":"Ein Tag im Leben von","jahr":"2018","lohn":"400","sozialleistungen":"","spesen":"nein","abrechnung":"pauschal","zeichen":"3500-4000 Zeichen","auftrag":"eigene Geschichte","infos":"","logo":"dasmagazin"},{"medium":"Das Magazin","ressort":"","jahr":"2017","lohn":"1500","sozialleistungen":"weiss nicht mehr","spesen":"nein","abrechnung":"pauschal","zeichen":"14000 Zeichen","auftrag":"eigene Geschichte","infos":"Auslandreportage mit mehreren Reiseorten","logo":"dasmagazin"},{"medium":"Der Bund","ressort":"Bern","jahr":"2018","lohn":"33 Franken pro Stunde","sozialleistungen":"AHV und ALV","spesen":"nein","abrechnung":"pro Stunde","zeichen":"","auftrag":"","infos":"bei allen Arten von freier Mitarbeit gilt der Stundenansatz","logo":"derbund"},{"medium":"Der Bund","ressort":"Kultur","jahr":"2018","lohn":"250","sozialleistungen":"","spesen":"","abrechnung":"pro Zeichen \/pro Stunde","zeichen":"4000 Zeichen","auftrag":"Auftragsarbeit","infos":"","logo":"derbund"},{"medium":"Der Bund","ressort":"Kultur","jahr":"2018","lohn":"450","sozialleistungen":"","spesen":"","abrechnung":"pro Zeichen \/pro Stunde","zeichen":"7000 Zeichen","auftrag":"Auftragsarbeit","infos":"","logo":"derbund"},{"medium":"Der Bund","ressort":"Lokal","jahr":"2018","lohn":"33 Franken pro Stunde","sozialleistungen":"AHV, ALV, PK","spesen":"Reisekosten","abrechnung":"pro Stunde","zeichen":"unterschiedlich","auftrag":"beides","infos":"","logo":"derbund"},{"medium":"Der Bund","ressort":"Zentralressort (Abschlussredaktion)","jahr":"2018","lohn":"40 Franken pro Stunde","sozialleistungen":"AHV, ALV und PK","spesen":"","abrechnung":"pro Stunde","zeichen":"","auftrag":"Auftragsarbeit","infos":"Redigier- und Layoutarbeit","logo":"derbund"},{"medium":"Edito","ressort":"","jahr":"2018","lohn":"200","sozialleistungen":"weiss nicht mehr","spesen":"","abrechnung":"pauschal","zeichen":"4000 Zeichen","auftrag":"Auftragsarbeit","infos":"","logo":"edito"},{"medium":"Freiburger Nachrichten","ressort":"Kultur","jahr":"2018","lohn":"200","sozialleistungen":"keine","spesen":"","abrechnung":"pauschal","zeichen":"2500-3000 Zeichen","auftrag":"Auftragsarbeit","infos":"Es handelt sich um Kritiken. Gleiches Honorar f\u00fcr unterschiedliche L\u00e4nge. Jeweils Besuch der Kulturveranstaltung (Theater, Ausstellung etc.) mit Vorrecherche","logo":"freiburgernachrichten"},{"medium":"Freiburger Nachrichten","ressort":"Kultur","jahr":"2018","lohn":"220","sozialleistungen":"keine","spesen":"ja (Kaffee w\u00e4hrend Interview)","abrechnung":"pauschal","zeichen":"3500 Zeichen","auftrag":"Auftragsarbeit","infos":"Besuch einer Abendveranstaltung, ein Interview mit dem Leiter und Interviews mit Teilnehmenden. Daf\u00fcr gab es etwas mehr (20 Fr.) als die \u00fcbliche Pauschale von 200 Fr.","logo":"freiburgernachrichten"},{"medium":"Landbote","ressort":"Region","jahr":"2015-2017","lohn":"150","sozialleistungen":"AHV","spesen":"nein","abrechnung":"pauschal","zeichen":"3500 Zeichen","auftrag":"meist Auftragsarbeiten","infos":"","logo":"landbote"},{"medium":"Landbote","ressort":"Stadtkultur","jahr":"2017","lohn":"140","sozialleistungen":"keine","spesen":"","abrechnung":"pauschal","zeichen":"4500 Zeichen","auftrag":"eigene Geschichte","infos":"","logo":"landbote"},{"medium":"Medienwoche","ressort":"Ausland","jahr":"2018","lohn":"500","sozialleistungen":"keine","spesen":"","abrechnung":"pauschal","zeichen":"6000 Zeichen","auftrag":"eigene Geschichte","infos":"","logo":"medienwoche"},{"medium":"Migros Magazin","ressort":"Inland","jahr":"2018","lohn":"1050","sozialleistungen":"AHV\/IV, EO und PK","spesen":"ja","abrechnung":"Tagesansatz","zeichen":"3000 Zeichen","auftrag":"Auftragsarbeit","infos":"","logo":"migrosmagazin"},{"medium":"NZZ","ressort":"Panorama","jahr":"2018","lohn":"600","sozialleistungen":"AHV und PK","spesen":"nein","abrechnung":"pauschal","zeichen":"7000 Zeichen","auftrag":"eigene Geschichte","infos":"","logo":"nzz"},{"medium":"NZZ","ressort":"Panorama","jahr":"2018","lohn":"800","sozialleistungen":"AHV und PK","spesen":"","abrechnung":"pauschal","zeichen":"6000 Zeichen plus ein Bild","auftrag":"eigene Geschichte","infos":"","logo":"nzz"},{"medium":"NZZ","ressort":"Ausland","jahr":"2018","lohn":"200","sozialleistungen":"AHV und PK","spesen":"nein","abrechnung":"pauschal","zeichen":"3000 Zeichen","auftrag":"eigene Geschichte","infos":"tagesaktuell, nicht aufw\u00e4ndig","logo":"nzz"},{"medium":"NZZ","ressort":"Wochenendbund","jahr":"2017","lohn":"800","sozialleistungen":"nein","spesen":"","abrechnung":"pauschal","zeichen":"eine Seite","auftrag":"eigene Geschichte","infos":"","logo":"nzz"},{"medium":"NZZ","ressort":"Panorama","jahr":"2018","lohn":"500","sozialleistungen":"AHV und ALV","spesen":"","abrechnung":"pauschal","zeichen":"5500 Zeichen","auftrag":"eigene Geschichte","infos":"","logo":"nzz"},{"medium":"NZZ","ressort":"Panorama","jahr":"2018","lohn":"350","sozialleistungen":"AHV und ALV","spesen":"","abrechnung":"pauschal","zeichen":"3500 Zeichen","auftrag":"eigene Geschichte","infos":"","logo":"nzz"},{"medium":"NZZ","ressort":"Lokal, Inland, Sport, Vermischtes","jahr":"2017","lohn":"400","sozialleistungen":"alle","spesen":"ja","abrechnung":"pro Tag (400)","zeichen":"","auftrag":"beides","infos":"zus\u00e4tzliches Fixum pro Monat von 400.-, egal wie viel ich schrieb, Teil meiner \"Anstellung\" als fester freier Mitarbeiter","logo":"nzz"},{"medium":"NZZ","ressort":"Panorama","jahr":"2018","lohn":"550","sozialleistungen":"keine","spesen":"nein","abrechnung":"pauschal","zeichen":"6000 Zeichen","auftrag":"eigene Geschichte","infos":"total Arbeitsaufwand: ca. 10 Stunden","logo":"nzz"},{"medium":"NZZ am Sonntag","ressort":"Gesellschaft","jahr":"2016","lohn":"1500","sozialleistungen":"AHV und ALV","spesen":"Beitrag an Flug","abrechnung":"pauschal","zeichen":"","auftrag":"eigene Geschichte","infos":"Reportage, aufw\u00e4ndige Recherche","logo":"nzzas"},{"medium":"NZZ am Sonntag","ressort":"Gesellschaft","jahr":"2015","lohn":"2000","sozialleistungen":"keine","spesen":"Beitrag an Flug und Transport","abrechnung":"pauschal","zeichen":"","auftrag":"eigene Geschichte","infos":"Auslandsreportage, grosse Recherche","logo":"nzzas"},{"medium":"NZZ am Sonntag","ressort":"Gesellschaft","jahr":"2017","lohn":"2000","sozialleistungen":"keine","spesen":"nein","abrechnung":"pauschal","zeichen":"","auftrag":"eigene Geschichte","infos":"aufw\u00e4ndige Recherche","logo":"nzzas"},{"medium":"NZZ am Sonntag","ressort":"Wissen","jahr":"2018","lohn":"700","sozialleistungen":"AHV und PK","spesen":"","abrechnung":"","zeichen":"5500 Zeichen","auftrag":"eigene Geschichte","infos":"","logo":"nzzas"},{"medium":"NZZ am Sonntag","ressort":"Wissen","jahr":"2018","lohn":"1200","sozialleistungen":"AHV und PK","spesen":"nein","abrechnung":"pauschal","zeichen":"7000 Zeichen","auftrag":"eigene Geschichte","infos":"","logo":"nzzas"},{"medium":"NZZ am Sonntag","ressort":"Gesellschaft","jahr":"2016","lohn":"1500","sozialleistungen":"keine","spesen":"Zug","abrechnung":"pauschal","zeichen":"13300 Zeichen","auftrag":"eigene Geschichte","infos":"bei der NZZ (Gesellschaft) erhielt ich, egal wie viel Aufwand, f\u00fcr einen Auftrag immer 1500.","logo":"nzzas"},{"medium":"NZZ am Sonntag","ressort":"Freizeitsport","jahr":"2018","lohn":"600","sozialleistungen":"keine","spesen":"","abrechnung":"pauschal","zeichen":"6400","auftrag":"eigene Geschichte","infos":"","logo":"nzzas"},{"medium":"NZZ am Sonntag","ressort":"Feuilleton","jahr":"2017","lohn":"800","sozialleistungen":"AHV","spesen":"nein","abrechnung":"pauschal","zeichen":"8000 Zeichen","auftrag":"eigene Geschichte","infos":"","logo":"nzzas"},{"medium":"Obersee Nachrichten","ressort":"Interview","jahr":"2018","lohn":"300","sozialleistungen":"keine","spesen":"","abrechnung":"pauschal","zeichen":"6500 Zeichen","auftrag":"Auftragsarbeit","infos":"","logo":"oberseenachrichten"},{"medium":"Obersee Nachrichten","ressort":"Fokus","jahr":"2018","lohn":"350","sozialleistungen":"keine","spesen":"","abrechnung":"pauschal","zeichen":"3500 Zeichen","auftrag":"beides","infos":"inklusive Strassenumfrage (4 Teilnehmer, mit Foto)","logo":"oberseenachrichten"},{"medium":"Oltner Stadtanzeiger","ressort":"Im Gespr\u00e4ch \/ Stadt \/ R\u00fcckblick","jahr":"2018","lohn":"150","sozialleistungen":"AHV\/IV, ALV, NBUV, PK","spesen":"nein","abrechnung":"pauschal","zeichen":"4500-5000 Zeichen","auftrag":"Auftragsarbeit","infos":"circa 4 Stunden Aufwand (exkl. An- und R\u00fcckreise)","logo":"oltnerstadtanzeiger"},{"medium":"Radio SRF2 Kultur","ressort":"Aktualit\u00e4t","jahr":"2018","lohn":"400","sozialleistungen":"AHV","spesen":"","abrechnung":"pauschal","zeichen":"3.30-4 Minuten","auftrag":"beides","infos":"","logo":"srf2kultur"},{"medium":"Rundschau (Effingermedien)","ressort":"Region","jahr":"2018","lohn":"100-140","sozialleistungen":"AHV","spesen":"","abrechnung":"pauschal","zeichen":"3500 Zeichen","auftrag":"Auftragsarbeit","infos":"Meistens Besuch eines Anlasses oder Interview, Zeitaufwand inkl. schreiben ca. 4 Stunden","logo":"effingermedien"},{"medium":"Schaffhauser Nachrichten","ressort":"Region","jahr":"2018","lohn":"80 Rappen pro Zeile (\u00e0 35Z) oder 80 Franken pro Anlass","sozialleistungen":"","spesen":"","abrechnung":"pro Zeile oder pauschal pro Anlass","zeichen":"oft kleinere Artikel","auftrag":"","infos":"","logo":"schaffhausernachrichten"},{"medium":"Schweizer Familie","ressort":"","jahr":"2018","lohn":"1500","sozialleistungen":"AHV und PK","spesen":"Zug","abrechnung":"pauschal","zeichen":"13500 Zeichen","auftrag":"eigene Geschichte","infos":"sehr aufw\u00e4ndige Recherche","logo":"schweizerfamilie"},{"medium":"Schweizer Journalist","ressort":"","jahr":"2015","lohn":"800","sozialleistungen":"","spesen":"","abrechnung":"pauschal","zeichen":"7500 Zeichen","auftrag":"","infos":"","logo":"schweizerjournalist"},{"medium":"Schweizer Journalist","ressort":"","jahr":"2015","lohn":"800","sozialleistungen":"","spesen":"","abrechnung":"pauschal","zeichen":"9000 Zeichen","auftrag":"","infos":"","logo":"schweizerjournalist"},{"medium":"sda","ressort":"Kultur","jahr":"2018","lohn":"330","sozialleistungen":"","spesen":"ja","abrechnung":"pro Zeichen","zeichen":"4500 Zeichen","auftrag":"Auftragsarbeit","infos":"","logo":"sda"},{"medium":"sda","ressort":"Kultur","jahr":"2018","lohn":"780","sozialleistungen":"AHV und ALV","spesen":"Zug und Verpflegung","abrechnung":"pro Stunde","zeichen":"3000-4500 Zeichen","auftrag":"Auftragsarbeit","infos":"Aufw\u00e4ndige Portr\u00e4ts mit Lekt\u00fcre, Treffen der Autoren und Videointerview zusammen mit Keystone. Die Artikel und das Keystone-Video k\u00f6nnen theoretisch in allen Medien erscheinen, die das Angebot der SDA abonniert haben. Zweitverwertungs-Honorar gibt es folglich nicht. Ist aber nicht unbedingt repr\u00e4sentativ f\u00fcr die ganze SDA oder das Kulturressort, weil diese Literatur-Reihe von der Gottlieb und Hans Vogt-Stiftung mit einem Medienf\u00f6rderungsbeitrag unterst\u00fctzt wird.","logo":"sda"},{"medium":"Sonntagsblick Magazin","ressort":"Magazin","jahr":"2018","lohn":"1800","sozialleistungen":"AHV und ALV","spesen":"","abrechnung":"pauschal","zeichen":"","auftrag":"eigene Geschichte","infos":"Auflandreportage, hoher Rechercheaufwand","logo":"sobli"},{"medium":"Sonntagsblick Magazin","ressort":"","jahr":"2018","lohn":"1000","sozialleistungen":"nein","spesen":"ja","abrechnung":"pauschal","zeichen":"drei Seiten inkl. Bildern","auftrag":"eigene Geschichte","infos":"","logo":"sobli"},{"medium":"SRG SSR","ressort":"RTS Temps pr\u00e9sent","jahr":"2018","lohn":"1950","sozialleistungen":"AHV, ALV, EO und IV","spesen":"","abrechnung":"Tagesansatz","zeichen":"mehrt\u00e4giger Rechercheauftrag f\u00fcr einen Dokumentarfilm","auftrag":"Auftragsarbeit","infos":"","logo":"srg"},{"medium":"Stil Magazin (NZZ)","ressort":"Reisen","jahr":"","lohn":"600","sozialleistungen":"keine","spesen":"","abrechnung":"pauschal","zeichen":"5500 Zeichen","auftrag":"eigene Geschichte","infos":"Auslandsreise, 3 Tage Aufwand","logo":"stil"},{"medium":"Stil Magazin (NZZ)","ressort":"Reisen","jahr":"2018","lohn":"300","sozialleistungen":"keine","spesen":"","abrechnung":"pauschal","zeichen":"3500 Zeichen","auftrag":"Auftragsarbeit","infos":"inkl. Zweitverwertung online","logo":"stil"},{"medium":"Surprise","ressort":"","jahr":"2018","lohn":"400","sozialleistungen":"AHV, ALV und PK","spesen":"nein","abrechnung":"pauschal","zeichen":"","auftrag":"eigene Geschichte","infos":"Zweitpublikation","logo":"surprise"},{"medium":"Surprise","ressort":"","jahr":"2017","lohn":"400","sozialleistungen":"keine","spesen":"","abrechnung":"pauschal","zeichen":"10000 Zeichen","auftrag":"eigene Geschichte","infos":"","logo":"surprise"},{"medium":"Swissinfo","ressort":"Ausland","jahr":"2018","lohn":"700","sozialleistungen":"AHV und PK","spesen":"","abrechnung":"pauschal","zeichen":"7000 Zeichen","auftrag":"eigene Geschichte","infos":"","logo":"swi"},{"medium":"Swissinfo","ressort":"Ausland","jahr":"2018","lohn":"200","sozialleistungen":"AHV und PK","spesen":"nein","abrechnung":"pauschal","zeichen":"4000 Zeichen","auftrag":"eigene Geschichte","infos":"Zweitpublikation","logo":"swi"},{"medium":"Swissinfo","ressort":"Inland","jahr":"2018","lohn":"700","sozialleistungen":"AHV, ALV und PK","spesen":"Zug","abrechnung":"pauschal","zeichen":"6000 Zeichen","auftrag":"Auftragsarbeit","infos":"","logo":"swi"},{"medium":"Tagblatt der Stadt Z\u00fcrich","ressort":"","jahr":"2018","lohn":"200","sozialleistungen":"","spesen":"","abrechnung":"200.- pro Seite\/ 400.- f\u00fcr Doppelseite","zeichen":"","auftrag":"beides","infos":"","logo":"tablattzuerich"},{"medium":"Tages-Anzeiger","ressort":"Z\u00fcrich","jahr":"2017","lohn":"500","sozialleistungen":"AHV, ALV und PK","spesen":"nein","abrechnung":"pauschal","zeichen":"7000 Zeichen","auftrag":"eigene Geschichte","infos":"","logo":"tagi"},{"medium":"Tages-Anzeiger","ressort":"Online","jahr":"","lohn":"400","sozialleistungen":"AHV","spesen":"nein","abrechnung":"Tagesansatz","zeichen":"","auftrag":"","infos":"","logo":"tagi"},{"medium":"Tages-Anzeiger","ressort":"Inland","jahr":"2017","lohn":"800","sozialleistungen":"AHV, ALV, PK","spesen":"","abrechnung":"pauschal","zeichen":"eine Seite","auftrag":"eigene Geschichte","infos":"Drei Tage Aufwand","logo":""},{"medium":"thurgaukultur.ch","ressort":"","jahr":"2018","lohn":"200","sozialleistungen":"keine","spesen":"nein","abrechnung":"pauschal","zeichen":"unterschiedlich","auftrag":"beides","infos":"Honorare f\u00fcr Textbeitr\u00e4ge sind pauschal 200 Franken, kein zus\u00e4tzliches Honorar f\u00fcr eigene Bilder","logo":"thurgaukultur"},{"medium":"Tierwelt","ressort":"Reisen","jahr":"2018","lohn":"600","sozialleistungen":"keine","spesen":"","abrechnung":"300 Franken pro Seite","zeichen":"6000 Zeichen","auftrag":"eigene Geschichte","infos":"","logo":"tierwelt"},{"medium":"Tierwelt","ressort":"","jahr":"2018","lohn":"600","sozialleistungen":"AHV und PK","spesen":"Zug","abrechnung":"300 Franken pro Seite","zeichen":"6000 Zeichen","auftrag":"eigene Geschichte","infos":"","logo":"tierwelt"},{"medium":"Toggenburger Zeitung","ressort":"Region","jahr":"2018","lohn":"200","sozialleistungen":"keine","spesen":"","abrechnung":"pauschal","zeichen":"3000-4000 Zeichen","auftrag":"beides","infos":"es gibt immer 200 Franken, egal wie gross der Aufwand ist.\u00a0","logo":"toz"},{"medium":"Vice Schweiz","ressort":"","jahr":"2017","lohn":"300","sozialleistungen":"keine","spesen":"","abrechnung":"pauschal","zeichen":"13000 Zeichen","auftrag":"Auftragsarbeit","infos":"musste unterschrieben werden: \"Hiermit erkl\u00e4re ich, dass ich auf AHV\/IV\/EO- und ALV-Beitr\u00e4ge aus dem Arbeitsverh\u00e4ltnis mit VICE Switzerland GmbH verzichte, da es sich um eine geringf\u00fcgige Entsch\u00e4digung f\u00fcr Nebenerwerb handelt, welche j\u00e4hrlich unter CHF 2'300.00 liegt.\"","logo":"vice"},{"medium":"Vice Schweiz","ressort":"","jahr":"2017","lohn":"250","sozialleistungen":"keine","spesen":"Zug","abrechnung":"pauschal","zeichen":"7600 Zeichen","auftrag":"eigene Geschichte","infos":"","logo":"vice"},{"medium":"Vice Schweiz","ressort":"","jahr":"2017","lohn":"250","sozialleistungen":"keine","spesen":"Zug","abrechnung":"pauschal","zeichen":"7200 Zeichen","auftrag":"eigene Geschichte","infos":"","logo":"vice"},{"medium":"Vice Schweiz","ressort":"","jahr":"2017","lohn":"450","sozialleistungen":"keine","spesen":"Zug","abrechnung":"pauschal","zeichen":"11000 Zeichen","auftrag":"eigene Geschichte","infos":"inkl. Fotos","logo":"vice"},{"medium":"Wilerzeitung","ressort":"Lokal","jahr":"2018","lohn":"150","sozialleistungen":"","spesen":"Autospesen 0.70Fr.\/km","abrechnung":"pauschal","zeichen":"3000 Zeichen","auftrag":"Auftragsarbeit","infos":"tagesaktueller Bericht","logo":"wilerzeitung"},{"medium":"WOZ","ressort":"Ausland","jahr":"2018","lohn":"500","sozialleistungen":"AHV und PK","spesen":"Transport, \u00dcbersetzer","abrechnung":"pauschal","zeichen":"10000 Zeichen","auftrag":"eigene Geschichte","infos":"","logo":"woz"},{"medium":"WOZ","ressort":"Ausland","jahr":"2018","lohn":"525","sozialleistungen":"AHV, ALV und PK","spesen":"Beitrag an Flug und Unterkunft","abrechnung":"pro Zeile","zeichen":"","auftrag":"eigene Geschichte","infos":"Auslandsreportage, aufw\u00e4ndige Recherche","logo":"woz"},{"medium":"WOZ","ressort":"","jahr":"2018","lohn":"500","sozialleistungen":"AHV und ALV","spesen":"","abrechnung":"pauschal","zeichen":"6500 Zeichen","auftrag":"eigene Geschichte","infos":"eher aufw\u00e4ndig, mehrere Treffen","logo":"woz"},{"medium":"WOZ","ressort":"Ausland","jahr":"2017","lohn":"500","sozialleistungen":"AHV, ALV, EO, NBUV","spesen":"Beitrag an Flug und Unterkunft","abrechnung":"","zeichen":"10000 Zeichen","auftrag":"eigene Geschichte","infos":"aufw\u00e4ndige Auslandrecherche","logo":"woz"},{"medium":"WOZ","ressort":"Inland","jahr":"2018","lohn":"1075","sozialleistungen":"AHV und ALV","spesen":"Anteil an Unterkunft und \u00dcbersetzer","abrechnung":"pro Zeile + Pauschale f\u00fcr Extraaufwand","zeichen":"10000 Zeichen","auftrag":"eigene Geschichte","infos":"Auslandreise, Artikel mehrmals angepasst","logo":"woz"},{"medium":"WOZ","ressort":"","jahr":"2018","lohn":"290","sozialleistungen":"","spesen":"","abrechnung":"pro Zeile","zeichen":"5500 Zeichen","auftrag":"Auftragsarbeit","infos":"","logo":"woz"},{"medium":"Z Magazin (NZZ)","ressort":"Reisen","jahr":"2018","lohn":"900","sozialleistungen":"keine","spesen":"","abrechnung":"pauschal","zeichen":"9000 Zeichen","auftrag":"Auftragsarbeit","infos":"","logo":"zmagazin"},{"medium":"ZEIT Schweiz","ressort":"","jahr":"2014","lohn":"400","sozialleistungen":"","spesen":"","abrechnung":"pauschal","zeichen":"6500 Zeichen","auftrag":"","infos":"","logo":"diezeit"},{"medium":"ZEIT Schweiz","ressort":"","jahr":"2017","lohn":"600","sozialleistungen":"AHV","spesen":"nein","abrechnung":"pauschal","zeichen":"8000 Zeichen","auftrag":"eigene Geschichte","infos":"","logo":"diezeit"},{"medium":"Z\u00fcrichsee Zeitung","ressort":"Region","jahr":"2018","lohn":"170","sozialleistungen":"keine","spesen":"","abrechnung":"pauschal","zeichen":"3000-4000 Zeichen","auftrag":"Auftragsarbeit","infos":"Meist handelt es sich um Nachberichterstattungen kultureller Anl\u00e4sse","logo":"zuerichseezeitung"},{"medium":"Z\u00fcrichsee Zeitung","ressort":"Bezirk Horgen","jahr":"2018","lohn":"170","sozialleistungen":"AHV, ALV, NBU","spesen":"nein","abrechnung":"pauschal","zeichen":"3700 Zeichen","auftrag":"Auftragsarbeit","infos":"Tagesaktueller Bericht. Ganzer Vormittag vor Ort, von Nachmittag bis Abend am Schreiben.","logo":"zuerichseezeitung"}]}